arangodb-0.0.12-py2.7-nspkg.pth
arangodb/db.py
arangodb/query.py
arangodb/util.py
arangodb/cursor.py
arangodb/exc.py
arangodb/api.py
arangodb/graph.py
arangodb/meta.py
arangodb-0.0.12.dist-info/top_level.txt
arangodb-0.0.12.dist-info/METADATA
arangodb-0.0.12.dist-info/DESCRIPTION.rst
arangodb-0.0.12.dist-info/namespace_packages.txt
arangodb-0.0.12.dist-info/WHEEL
arangodb-0.0.12.dist-info/metadata.json
arangodb-0.0.12.dist-info/RECORD
