Metadata-Version: 1.1
Name: arangodb
Version: 0.0.12
Summary: A Python client for ArangoDB REST API.
Home-page: https://github.com/diefans/python-arangodb
Author: Oliver Berger
Author-email: diefans@gmail.com
License: Apache License Version 2.0
Keywords: ArangoDB REST API Requests graph nosql database AQL
Platform: UNKNOWN
Classifier: Development Status :: 4 - Beta
Classifier: License :: OSI Approved :: Apache Software License
Classifier: Programming Language :: Python :: 2.7
Classifier: Topic :: Database
